hello_demo/__init__.py
hello_demo/cli.py
hello_demo/hello_demo.py
hello_demo-0.1.7.dist-info/METADATA
hello_demo-0.1.7.dist-info/RECORD
hello_demo-0.1.7.dist-info/WHEEL
hello_demo-0.1.7.dist-info/entry_points.txt
hello_demo-0.1.7.dist-info/top_level.txt
